LCFLib/NetworkController.py
LCFLib/__init__.py
LoCyanFrpLib-1.0.0.dist-info/LICENSE
LoCyanFrpLib-1.0.0.dist-info/METADATA
LoCyanFrpLib-1.0.0.dist-info/WHEEL
LoCyanFrpLib-1.0.0.dist-info/top_level.txt
LoCyanFrpLib-1.0.0.dist-info/RECORD
