Metadata-Version: 2.1
Name: LoCyanFrpLib
Version: 1.0.0
Summary: UNKNOWN
Home-page: https://github.com/LxHTT/LoCyanFrpLib
Author: LxHTT
Author-email: lxhtt@vip.qq.com
License: MIT
Project-URL: Documentation, https://github.com/LxHTT/LoCyanFrpLib/blob/master/README.md
Project-URL: Source Code, https://github.com/LxHTT/LoCyanFrpLib
Project-URL: Bug Tracker, https://github.com/LxHTT/LoCyanFrpLib/issues
Platform: UNKNOWN
Classifier: Programming Language :: Python :: 3.8
Classifier: License :: OSI Approved :: MIT License
Classifier: Operating System :: OS Independent
Requires-Python: >=3.7, <=3.11
Requires-Dist: requests >=2.31.0
